Workbook

Sheet DCF
A1: ALPHABET INC. (NASDAQ: GOOGL / GOOG) — DISCOUNTED CASH FLOW MODEL
A2: Ticker: GOOG | FYE: 31 December | Valuation date: 1-Jan-2026 (FY2025 year-end balance sheet) | $ in millions except per-share
A3: FY2026E–FY2030E assumptions mirror GOOG_3_Statement_Model.xlsx (Base/Upside/Downside). FY2031E–FY2035E are a capex-normalisation extension built for this DCF.
A4: Blue font = hardcoded input | Black font = formula | Green font = link to WACC sheet
A6: CASE SELECTOR
A7: Selected case (1 = Bear · 2 = Base · 3 = Bull) | B7: 2 | C7: =IF($B$7=1,"BEAR",IF($B$7=2,"BASE","BULL")) -> BASE
A9: MARKET DATA & VALUATION INPUTS
A10: Current share price ($) | B10: 335.31
A11: Diluted shares outstanding (m) | B11: 12450
A12: Market capitalisation ($m) | B12: =B10*B11 -> 4174609.5
A13: Cash, equivalents & marketable securities ($m) | B13: 126843
A14: Total debt ($m) | B14: 46547
A15: Net cash / (net debt) ($m) | B15: =B13-B14 -> 80296
A16: WACC — selected (from WACC sheet) | B16: =WACC!B36 -> 0.0925
A17: Terminal capex as multiple of terminal D&A (x) | B17: 1.15
A18: Change in NWC as % of change in revenue | B18: -0.018
A19: Valuation roll-forward to 8-Sep-2026 (years) | B19: 0.685
A20: BEAR CASE ASSUMPTIONS (= 3-statement model Downside, extended)
A21: Assumption | G21: FY2026E | H21: FY2027E | I21: FY2028E | J21: FY2029E | K21: FY2030E | L21: FY2031E | M21: FY2032E | N21: FY2033E | O21: FY2034E | P21: FY2035E
A22: Revenue growth (%) | G22: 0.185 | H22: 0.12 | I22: 0.09 | J22: 0.07 | K22: 0.06 | L22: 0.05 | M22: 0.045 | N22: 0.04 | O22: 0.035 | P22: 0.03
A23: Cost of revenues ex-D&A (% of revenue) | G23: 0.345 | H23: 0.355 | I23: 0.365 | J23: 0.372 | K23: 0.378 | L23: 0.38 | M23: 0.381 | N23: 0.382 | O23: 0.382 | P23: 0.383
A24: Research & development ex-D&A (% of revenue) | G24: 0.15 | H24: 0.156 | I24: 0.161 | J24: 0.165 | K24: 0.168 | L24: 0.169 | M24: 0.17 | N24: 0.17 | O24: 0.171 | P24: 0.171
A25: Sales & marketing (% of revenue) | G25: 0.071 | H25: 0.073 | I25: 0.075 | J25: 0.076 | K25: 0.077 | L25: 0.077 | M25: 0.078 | N25: 0.078 | O25: 0.078 | P25: 0.078
A26: General & administrative (% of revenue) | G26: 0.049 | H26: 0.05 | I26: 0.051 | J26: 0.052 | K26: 0.053 | L26: 0.053 | M26: 0.053 | N26: 0.054 | O26: 0.054 | P26: 0.054
A27: Depreciation (% of beginning net PP&E) | G27: 0.133 | H27: 0.158 | I27: 0.178 | J27: 0.192 | K27: 0.2 | L27: 0.2 | M27: 0.195 | N27: 0.19 | O27: 0.185 | P27: 0.18
A28: Capital expenditure ($m) | G28: 200000 | H28: 250000 | I28: 230000 | J28: 200000 | K28: 180000 | L28: 175000 | M28: 175000 | N28: 180000 | O28: 185000 | P28: 190000
A29: Effective tax rate (%) | G29: 0.195 | H29: 0.2 | I29: 0.205 | J29: 0.205 | K29: 0.205 | L29: 0.205 | M29: 0.205 | N29: 0.205 | O29: 0.205 | P29: 0.205
A30: Terminal growth rate (%) | G30: 0.02
A31: WACC spread vs. selected WACC (%) | G31: 0.01
A33: BASE CASE ASSUMPTIONS (= 3-statement model Base, extended)
A34: Assumption | G34: FY2026E | H34: FY2027E | I34: FY2028E | J34: FY2029E | K34: FY2030E | L34: FY2031E | M34: FY2032E | N34: FY2033E | O34: FY2034E | P34: FY2035E
A35: Revenue growth (%) | G35: 0.21 | H35: 0.17 | I35: 0.14 | J35: 0.12 | K35: 0.11 | L35: 0.095 | M35: 0.08 | N35: 0.07 | O35: 0.06 | P35: 0.05
A36: Cost of revenues ex-D&A (% of revenue) | G36: 0.335 | H36: 0.332 | I36: 0.33 | J36: 0.328 | K36: 0.326 | L36: 0.324 | M36: 0.322 | N36: 0.32 | O36: 0.319 | P36: 0.318
A37: Research & development ex-D&A (% of revenue) | G37: 0.145 | H37: 0.144 | I37: 0.143 | J37: 0.142 | K37: 0.141 | L37: 0.14 | M37: 0.139 | N37: 0.138 | O37: 0.138 | P37: 0.137
A38: Sales & marketing (% of revenue) | G38: 0.069 | H38: 0.068 | I38: 0.067 | J38: 0.066 | K38: 0.065 | L38: 0.064 | M38: 0.063 | N38: 0.063 | O38: 0.062 | P38: 0.062
A39: General & administrative (% of revenue) | G39: 0.047 | H39: 0.045 | I39: 0.044 | J39: 0.043 | K39: 0.042 | L39: 0.041 | M39: 0.04 | N39: 0.04 | O39: 0.039 | P39: 0.039
A40: Depreciation (% of beginning net PP&E) | G40: 0.13 | H40: 0.15 | I40: 0.165 | J40: 0.175 | K40: 0.18 | L40: 0.18 | M40: 0.175 | N40: 0.17 | O40: 0.165 | P40: 0.16
A41: Capital expenditure ($m) | G41: 200000 | H41: 260000 | I41: 290000 | J41: 300000 | K41: 305000 | L41: 295000 | M41: 285000 | N41: 280000 | O41: 275000 | P41: 275000
A42: Effective tax rate (%) | G42: 0.19 | H42: 0.19 | I42: 0.19 | J42: 0.19 | K42: 0.19 | L42: 0.19 | M42: 0.19 | N42: 0.19 | O42: 0.19 | P42: 0.19
A43: Terminal growth rate (%) | G43: 0.03
A44: WACC spread vs. selected WACC (%) | G44: 0
A46: BULL CASE ASSUMPTIONS (= 3-statement model Upside, extended)
A47: Assumption | G47: FY2026E | H47: FY2027E | I47: FY2028E | J47: FY2029E | K47: FY2030E | L47: FY2031E | M47: FY2032E | N47: FY2033E | O47: FY2034E | P47: FY2035E
A48: Revenue growth (%) | G48: 0.235 | H48: 0.205 | I48: 0.18 | J48: 0.155 | K48: 0.14 | L48: 0.12 | M48: 0.105 | N48: 0.09 | O48: 0.075 | P48: 0.06
A49: Cost of revenues ex-D&A (% of revenue) | G49: 0.33 | H49: 0.322 | I49: 0.315 | J49: 0.31 | K49: 0.305 | L49: 0.302 | M49: 0.3 | N49: 0.298 | O49: 0.296 | P49: 0.295
A50: Research & development ex-D&A (% of revenue) | G50: 0.143 | H50: 0.14 | I50: 0.137 | J50: 0.135 | K50: 0.133 | L50: 0.132 | M50: 0.131 | N50: 0.13 | O50: 0.129 | P50: 0.128
A51: Sales & marketing (% of revenue) | G51: 0.068 | H51: 0.066 | I51: 0.064 | J51: 0.063 | K51: 0.062 | L51: 0.061 | M51: 0.06 | N51: 0.06 | O51: 0.059 | P51: 0.059
A52: General & administrative (% of revenue) | G52: 0.046 | H52: 0.043 | I52: 0.041 | J52: 0.04 | K52: 0.039 | L52: 0.038 | M52: 0.038 | N52: 0.037 | O52: 0.037 | P52: 0.036
A53: Depreciation (% of beginning net PP&E) | G53: 0.128 | H53: 0.143 | I53: 0.153 | J53: 0.16 | K53: 0.163 | L53: 0.163 | M53: 0.16 | N53: 0.157 | O53: 0.154 | P53: 0.15
A54: Capital expenditure ($m) | G54: 200000 | H54: 255000 | I54: 275000 | J54: 290000 | K54: 295000 | L54: 300000 | M54: 305000 | N54: 305000 | O54: 310000 | P54: 315000
A55: Effective tax rate (%) | G55: 0.185 | H55: 0.183 | I55: 0.18 | J55: 0.18 | K55: 0.18 | L55: 0.18 | M55: 0.18 | N55: 0.18 | O55: 0.18 | P55: 0.18
A56: Terminal growth rate (%) | G56: 0.035
A57: WACC spread vs. selected WACC (%) | G57: -0.0075
A59: LIVE ASSUMPTIONS — SELECTED CASE (CHOOSE() consolidation; all projections reference these rows)
A60: Assumption | G60: FY2026E | H60: FY2027E | I60: FY2028E | J60: FY2029E | K60: FY2030E | L60: FY2031E | M60: FY2032E | N60: FY2033E | O60: FY2034E | P60: FY2035E
A61: Revenue growth (%) | G61: =CHOOSE($B$7,G22,G35,G48) -> 0.21 | H61: =CHOOSE($B$7,H22,H35,H48) -> 0.17 | I61: =CHOOSE($B$7,I22,I35,I48) -> 0.14 | J61: =CHOOSE($B$7,J22,J35,J48) -> 0.12 | K61: =CHOOSE($B$7,K22,K35,K48) -> 0.11 | L61: =CHOOSE($B$7,L22,L35,L48) -> 0.095 | M61: =CHOOSE($B$7,M22,M35,M48) -> 0.08 | N61: =CHOOSE($B$7,N22,N35,N48) -> 0.07 | ... P61: =CHOOSE($B$7,P22,P35,P48) -> 0.05
A62: Cost of revenues ex-D&A (% of revenue) | G62: =CHOOSE($B$7,G23,G36,G49) -> 0.335 | H62: =CHOOSE($B$7,H23,H36,H49) -> 0.332 | I62: =CHOOSE($B$7,I23,I36,I49) -> 0.33 | J62: =CHOOSE($B$7,J23,J36,J49) -> 0.328 | K62: =CHOOSE($B$7,K23,K36,K49) -> 0.326 | L62: =CHOOSE($B$7,L23,L36,L49) -> 0.324 | M62: =CHOOSE($B$7,M23,M36,M49) -> 0.322 | N62: =CHOOSE($B$7,N23,N36,N49) -> 0.32 | ... P62: =CHOOSE($B$7,P23,P36,P49) -> 0.318
A63: Research & development ex-D&A (% of revenue) | G63: =CHOOSE($B$7,G24,G37,G50) -> 0.145 | H63: =CHOOSE($B$7,H24,H37,H50) -> 0.144 | I63: =CHOOSE($B$7,I24,I37,I50) -> 0.143 | J63: =CHOOSE($B$7,J24,J37,J50) -> 0.142 | K63: =CHOOSE($B$7,K24,K37,K50) -> 0.141 | L63: =CHOOSE($B$7,L24,L37,L50) -> 0.14 | M63: =CHOOSE($B$7,M24,M37,M50) -> 0.139 | N63: =CHOOSE($B$7,N24,N37,N50) -> 0.138 | ... P63: =CHOOSE($B$7,P24,P37,P50) -> 0.137
A64: Sales & marketing (% of revenue) | G64: =CHOOSE($B$7,G25,G38,G51) -> 0.069 | H64: =CHOOSE($B$7,H25,H38,H51) -> 0.068 | I64: =CHOOSE($B$7,I25,I38,I51) -> 0.067 | J64: =CHOOSE($B$7,J25,J38,J51) -> 0.066 | K64: =CHOOSE($B$7,K25,K38,K51) -> 0.065 | L64: =CHOOSE($B$7,L25,L38,L51) -> 0.064 | M64: =CHOOSE($B$7,M25,M38,M51) -> 0.063 | N64: =CHOOSE($B$7,N25,N38,N51) -> 0.063 | ... P64: =CHOOSE($B$7,P25,P38,P51) -> 0.062
A65: General & administrative (% of revenue) | G65: =CHOOSE($B$7,G26,G39,G52) -> 0.047 | H65: =CHOOSE($B$7,H26,H39,H52) -> 0.045 | I65: =CHOOSE($B$7,I26,I39,I52) -> 0.044 | J65: =CHOOSE($B$7,J26,J39,J52) -> 0.043 | K65: =CHOOSE($B$7,K26,K39,K52) -> 0.042 | L65: =CHOOSE($B$7,L26,L39,L52) -> 0.041 | M65: =CHOOSE($B$7,M26,M39,M52) -> 0.04 | N65: =CHOOSE($B$7,N26,N39,N52) -> 0.04 | ... P65: =CHOOSE($B$7,P26,P39,P52) -> 0.039
A66: Depreciation (% of beginning net PP&E) | G66: =CHOOSE($B$7,G27,G40,G53) -> 0.13 | H66: =CHOOSE($B$7,H27,H40,H53) -> 0.15 | I66: =CHOOSE($B$7,I27,I40,I53) -> 0.165 | J66: =CHOOSE($B$7,J27,J40,J53) -> 0.175 | K66: =CHOOSE($B$7,K27,K40,K53) -> 0.18 | L66: =CHOOSE($B$7,L27,L40,L53) -> 0.18 | M66: =CHOOSE($B$7,M27,M40,M53) -> 0.175 | N66: =CHOOSE($B$7,N27,N40,N53) -> 0.17 | ... P66: =CHOOSE($B$7,P27,P40,P53) -> 0.16
A67: Capital expenditure ($m) | G67: =CHOOSE($B$7,G28,G41,G54) -> 200000 | H67: =CHOOSE($B$7,H28,H41,H54) -> 260000 | I67: =CHOOSE($B$7,I28,I41,I54) -> 290000 | J67: =CHOOSE($B$7,J28,J41,J54) -> 300000 | K67: =CHOOSE($B$7,K28,K41,K54) -> 305000 | L67: =CHOOSE($B$7,L28,L41,L54) -> 295000 | M67: =CHOOSE($B$7,M28,M41,M54) -> 285000 | N67: =CHOOSE($B$7,N28,N41,N54) -> 280000 | ... P67: =CHOOSE($B$7,P28,P41,P54) -> 275000
A68: Effective tax rate (%) | G68: =CHOOSE($B$7,G29,G42,G55) -> 0.19 | H68: =CHOOSE($B$7,H29,H42,H55) -> 0.19 | I68: =CHOOSE($B$7,I29,I42,I55) -> 0.19 | J68: =CHOOSE($B$7,J29,J42,J55) -> 0.19 | K68: =CHOOSE($B$7,K29,K42,K55) -> 0.19 | L68: =CHOOSE($B$7,L29,L42,L55) -> 0.19 | M68: =CHOOSE($B$7,M29,M42,M55) -> 0.19 | N68: =CHOOSE($B$7,N29,N42,N55) -> 0.19 | ... P68: =CHOOSE($B$7,P29,P42,P55) -> 0.19
A69: Terminal growth rate (%) | G69: =CHOOSE($B$7,$G$30,$G$43,$G$56) -> 0.03
A70: WACC — selected case (%) | G70: =$B$16+CHOOSE($B$7,$G$31,$G$44,$G$57) -> 0.0925
A72: HISTORICAL REPORTED INCOME STATEMENT (as filed, FY2021A–FY2025A)
A73: ($m) | B73: FY2021A | C73: FY2022A | D73: FY2023A | E73: FY2024A | F73: FY2025A
A74: Revenues | B74: 257637 | C74: 282836 | D74: 307394 | E74: 350018 | F74: 402836
A75: Cost of revenues | B75: 110939 | C75: 126203 | D75: 133332 | E75: 146306 | F75: 162535
A76: Research and development | B76: 31562 | C76: 39500 | D76: 45427 | E76: 49326 | F76: 61087
A77: Sales and marketing | B77: 22912 | C77: 26567 | D77: 27917 | E77: 27808 | F77: 28693
A78: General and administrative | B78: 13510 | C78: 15724 | D78: 16425 | E78: 14188 | F78: 21482
A79: Income from operations | B79: 78714 | C79: 74842 | D79: 84293 | E79: 112390 | F79: 129039
A80: Depreciation of property and equipment | B80: 10273 | C80: 13475 | D80: 11946 | E80: 15311 | F80: 21136
A81: D&A allocated to cost of revenues (%) | B81: 0.85
A84: INCOME STATEMENT — HISTORICAL & PROJECTED
A85: ($m) | B85: FY2021A | C85: FY2022A | D85: FY2023A | E85: FY2024A | F85: FY2025A | G85: FY2026E | H85: FY2027E | I85: FY2028E | J85: FY2029E | K85: FY2030E | L85: FY2031E | M85: FY2032E | N85: FY2033E | O85: FY2034E | P85: FY2035E
A86: Revenue | B86: =B74 -> 257637 | C86: =C74 -> 282836 | D86: =D74 -> 307394 | E86: =E74 -> 350018 | F86: =F74 -> 402836 | G86: =F86*(1+G61) -> 487431.56 | H86: =G86*(1+H61) -> 570294.93 | I86: =H86*(1+I61) -> 650136.21 | J86: =I86*(1+J61) -> 728152.56 | K86: =J86*(1+K61) -> 808249.34 | L86: =K86*(1+L61) -> 885033.03 | M86: =L86*(1+M61) -> 955835.67 | N86: =M86*(1+N61) -> 1022744.2 | ... P86: =O86*(1+P61) -> 1138314.3
A87: Revenue growth % | C87: =C86/B86-1 -> 0.097808156 | D87: =D86/C86-1 -> 0.086827702 | E87: =E86/D86-1 -> 0.13866243 | F87: =F86/E86-1 -> 0.15090081 | G87: =G86/F86-1 -> 0.21 | H87: =H86/G86-1 -> 0.17 | I87: =I86/H86-1 -> 0.14 | J87: =J86/I86-1 -> 0.12 | ... P87: =P86/O86-1 -> 0.05
A88: Cost of revenues (ex-D&A) | B88: =B75-$B$81*B80 -> 102206.95 | C88: =C75-$B$81*C80 -> 114749.25 | D88: =D75-$B$81*D80 -> 123177.9 | E88: =E75-$B$81*E80 -> 133291.65 | F88: =F75-$B$81*F80 -> 144569.4 | G88: =G86*G62 -> 163289.57 | H88: =H86*H62 -> 189337.92 | I88: =I86*I62 -> 214544.95 | J88: =J86*J62 -> 238834.04 | K88: =K86*K62 -> 263489.29 | L88: =L86*L62 -> 286750.7 | M88: =M86*M62 -> 307779.09 | N88: =N86*N62 -> 327278.13 | ... P88: =P86*P62 -> 361983.93
A89: % of revenue | B89: =B88/B86 -> 0.39670913 | C89: =C88/C86 -> 0.40570949 | D89: =D88/D86 -> 0.40071667 | E89: =E88/E86 -> 0.3808137 | F89: =F88/F86 -> 0.35887905 | G89: =G88/G86 -> 0.335 | H89: =H88/H86 -> 0.332 | I89: =I88/I86 -> 0.33 | ... P89: =P88/P86 -> 0.318
A90: Research & development (ex-D&A) | B90: =B76-(1-$B$81)*B80 -> 30021.05 | C90: =C76-(1-$B$81)*C80 -> 37478.75 | D90: =D76-(1-$B$81)*D80 -> 43635.1 | E90: =E76-(1-$B$81)*E80 -> 47029.35 | F90: =F76-(1-$B$81)*F80 -> 57916.6 | G90: =G86*G63 -> 70677.576 | H90: =H86*H63 -> 82122.469 | I90: =I86*I63 -> 92969.479 | J90: =J86*J63 -> 103397.66 | K90: =K86*K63 -> 113963.16 | L90: =L86*L63 -> 123904.62 | M90: =M86*M63 -> 132861.16 | N90: =N86*N63 -> 141138.7 | ... P90: =P86*P63 -> 155949.05
A91: % of revenue | B91: =B90/B86 -> 0.11652461 | C91: =C90/C86 -> 0.13251054 | D91: =D90/D86 -> 0.1419517 | E91: =E90/E86 -> 0.13436266 | F91: =F90/F86 -> 0.14377216 | G91: =G90/G86 -> 0.145 | H91: =H90/H86 -> 0.144 | I91: =I90/I86 -> 0.143 | ... P91: =P90/P86 -> 0.137
A92: Sales & marketing | B92: =B77 -> 22912 | C92: =C77 -> 26567 | D92: =D77 -> 27917 | E92: =E77 -> 27808 | F92: =F77 -> 28693 | G92: =G86*G64 -> 33632.778 | H92: =H86*H64 -> 38780.055 | I92: =I86*I64 -> 43559.126 | J92: =J86*J64 -> 48058.069 | K92: =K86*K64 -> 52536.207 | L92: =L86*L64 -> 56642.114 | M92: =M86*M64 -> 60217.647 | N92: =N86*N64 -> 64432.883 | ... P92: =P86*P64 -> 70575.484
A93: % of revenue | B93: =B92/B86 -> 0.088931326 | C93: =C92/C86 -> 0.093930758 | D93: =D92/D86 -> 0.090818298 | E93: =E92/E86 -> 0.079447343 | F93: =F92/F86 -> 0.071227497 | G93: =G92/G86 -> 0.069 | H93: =H92/H86 -> 0.068 | I93: =I92/I86 -> 0.067 | ... P93: =P92/P86 -> 0.062
A94: General & administrative | B94: =B78 -> 13510 | C94: =C78 -> 15724 | D94: =D78 -> 16425 | E94: =E78 -> 14188 | F94: =F78 -> 21482 | G94: =G86*G65 -> 22909.283 | H94: =H86*H65 -> 25663.272 | I94: =I86*I65 -> 28605.993 | J94: =J86*J65 -> 31310.56 | K94: =K86*K65 -> 33946.472 | L94: =L86*L65 -> 36286.354 | M94: =M86*M65 -> 38233.427 | N94: =N86*N65 -> 40909.767 | ... P94: =P86*P65 -> 44394.256
A95: % of revenue | B95: =B94/B86 -> 0.05243812 | C95: =C94/C86 -> 0.055594055 | D95: =D94/D86 -> 0.053433053 | E95: =E94/E86 -> 0.040535058 | F95: =F94/F86 -> 0.053326912 | G95: =G94/G86 -> 0.047 | H95: =H94/H86 -> 0.045 | I95: =I94/I86 -> 0.044 | ... P95: =P94/P86 -> 0.039
A96: Total operating costs (ex-D&A) | B96: =B88+B90+B92+B94 -> 168650 | C96: =C88+C90+C92+C94 -> 194519 | D96: =D88+D90+D92+D94 -> 211155 | E96: =E88+E90+E92+E94 -> 222317 | F96: =F88+F90+F92+F94 -> 252661 | G96: =G88+G90+G92+G94 -> 290509.21 | H96: =H88+H90+H92+H94 -> 335903.71 | I96: =I88+I90+I92+I94 -> 379679.55 | ... P96: =P88+P90+P92+P94 -> 632902.73
A97: EBITDA | B97: =B86-B96 -> 88987 | C97: =C86-C96 -> 88317 | D97: =D86-D96 -> 96239 | E97: =E86-E96 -> 127701 | F97: =F86-F96 -> 150175 | G97: =G86-G96 -> 196922.35 | H97: =H86-H96 -> 234391.21 | I97: =I86-I96 -> 270456.67 | ... P97: =P86-P96 -> 505411.53
A98: EBITDA margin % | B98: =B97/B86 -> 0.34539682 | C98: =C97/C86 -> 0.31225516 | D98: =D97/D86 -> 0.31308028 | E98: =E97/E86 -> 0.36484124 | F98: =F97/F86 -> 0.37279439 | G98: =G97/G86 -> 0.404 | H98: =H97/H86 -> 0.411 | I98: =I97/I86 -> 0.416 | ... P98: =P97/P86 -> 0.444
A99: Depreciation & amortisation | B99: =B80 -> 10273 | C99: =C80 -> 13475 | D99: =D80 -> 11946 | E99: =E80 -> 15311 | F99: =F80 -> 21136 | G99: =-G112 -> 32057.61 | H99: =-H112 -> 62180.908 | I99: =-I112 -> 101039.15 | J99: =-J112 -> 140230.88 | K99: =-K112 -> 172995.92 | L99: =-L112 -> 196756.66 | M99: =-M112 -> 208483.78 | N99: =-N112 -> 215534.86 | ... P99: =-P112 -> 221997.58
A100: D&A % of revenue | B100: =B99/B86 -> 0.039873931 | C100: =C99/C86 -> 0.04764245 | D100: =D99/D86 -> 0.038862177 | E100: =E99/E86 -> 0.043743465 | F100: =F99/F86 -> 0.052468002 | G100: =G99/G86 -> 0.065768433 | H100: =H99/H86 -> 0.1090329 | I100: =I99/I86 -> 0.15541228 | ... P100: =P99/P86 -> 0.19502311
A101: EBIT | B101: =B97-B99 -> 78714 | C101: =C97-C99 -> 74842 | D101: =D97-D99 -> 84293 | E101: =E97-E99 -> 112390 | F101: =F97-F99 -> 129039 | G101: =G97-G99 -> 164864.74 | H101: =H97-H99 -> 172210.31 | I101: =I97-I99 -> 169417.52 | ... P101: =P97-P99 -> 283413.95
A102: EBIT margin % | B102: =B101/B86 -> 0.30552289 | C102: =C101/C86 -> 0.26461271 | D102: =D101/D86 -> 0.2742181 | E102: =E101/E86 -> 0.32109777 | F102: =F101/F86 -> 0.32032639 | G102: =G101/G86 -> 0.33823157 | H102: =H101/H86 -> 0.3019671 | I102: =I101/I86 -> 0.26058772 | ... P102: =P101/P86 -> 0.24897689
A103: Memo: reported income from operations | B103: =B79 -> 78714 | C103: =C79 -> 74842 | D103: =D79 -> 84293 | E103: =E79 -> 112390 | F103: =F79 -> 129039
A104: Taxes on EBIT | G104: =-G101*G68 -> -31324.301 | H104: =-H101*H68 -> -32719.958 | I104: =-I101*I68 -> -32189.328 | J104: =-J101*J68 -> -31601.056 | K104: =-K101*K68 -> -32550.477 | L104: =-L101*L68 -> -35091.59 | M104: =-M101*M68 -> -39569.509 | N104: =-N101*N68 -> -44355.468 | ... P104: =-P101*P68 -> -53848.65
A105: Effective tax rate % | G105: =-G104/G101 -> 0.19 | H105: =-H104/H101 -> 0.19 | I105: =-I104/I101 -> 0.19 | J105: =-J104/J101 -> 0.19 | K105: =-K104/K101 -> 0.19 | L105: =-L104/L101 -> 0.19 | M105: =-M104/M101 -> 0.19 | N105: =-N104/N101 -> 0.19 | ... P105: =-P104/P101 -> 0.19
A106: NOPAT | G106: =G101+G104 -> 133540.44 | H106: =H101+H104 -> 139490.35 | I106: =I101+I104 -> 137228.19 | J106: =J101+J104 -> 134720.29 | K106: =K101+K104 -> 138767.82 | L106: =L101+L104 -> 149600.99 | M106: =M101+M104 -> 168691.07 | N106: =N101+N104 -> 189094.37 | ... P106: =P101+P104 -> 229565.3
A107: PROPERTY & EQUIPMENT / DEPRECIATION ROLL-FORWARD
A108: ($m) | B108: FY2021A | C108: FY2022A | D108: FY2023A | E108: FY2024A | F108: FY2025A | G108: FY2026E | H108: FY2027E | I108: FY2028E | J108: FY2029E | K108: FY2030E | L108: FY2031E | M108: FY2032E | N108: FY2033E | O108: FY2034E | P108: FY2035E
...

Sheet WACC
A1: ALPHABET INC. — WEIGHTED AVERAGE COST OF CAPITAL
A2: Market data as of 4-Sep-2026 close | $ in millions | Blue = input, black = formula, green = link to DCF sheet
A4: COST OF EQUITY (CAPM)
A5: Risk-free rate (10Y US Treasury) | B5: 0.0477
A6: Levered beta (5-year monthly) | B6: 1.24
A7: Equity risk premium | B7: 0.055
A8: Cost of equity (CAPM) | B8: =B5+B6*B7 -> 0.1159
A10: COST OF DEBT
A11: Credit rating (Moody's / S&P) | B11: Aa2 / AA+
A12: Pre-tax cost of debt | B12: 0.0525
A13: Effective tax rate (live, from DCF) | B13: =DCF!G68 -> 0.19
A14: After-tax cost of debt | B14: =B12*(1-B13) -> 0.042525
A16: CAPITAL STRUCTURE (market values)
A17: Current share price ($) | B17: =DCF!B10 -> 335.31
A18: Diluted shares outstanding (m) | B18: =DCF!B11 -> 12450
A19: Market capitalisation ($m) | B19: =B17*B18 -> 4174609.5
A20: Total debt ($m) | B20: =DCF!B14 -> 46547
A21: Cash, equivalents & marketable securities ($m) | B21: =DCF!B13 -> 126843
A22: Net cash / (net debt) ($m) | B22: =B21-B20 -> 80296
A23: Total capitalisation — market equity + gross debt ($m) | B23: =B19+B20 -> 4221156.5
A24: Note: WACC weights use GROSS debt (Alphabet is in a net cash position; net-debt weights would produce a negative debt weight and a WACC above the cost of equity). Net cash is credited in the DCF equity bridge instead.
A26: WACC CALCULATION
A27: Component | B27: Weight | C27: Cost | D27: Contribution
A28: Equity | B28: =B19/B23 -> 0.98897293 | C28: =B8 -> 0.1159 | D28: =B28*C28 -> 0.11462196
A29: Debt | B29: =B20/B23 -> 0.011027073 | C29: =B14 -> 0.042525 | D29: =B29*C29 -> 0.00046892627
A30: Total | B30: =B28+B29 -> 1 | D30: =D28+D29 -> 0.11509089
A31: WACC — CAPM output | B31: =D30 -> 0.11509089
A33: WACC SELECTION
A34: WACC method (1 = CAPM · 2 = Override) | B34: 2
A35: Override WACC (%) | B35: 0.0925
A36: WACC — SELECTED (used in DCF) | B36: =IF(B34=1,B31,B35) -> 0.0925
